weink
