Metadata-Version: 1.1
Name: weink
Version: 0.1.1
Summary: E-ink display library for waveshare screens
Home-page: https://github.com/FloppyDisck/e-ink-lib
Author: FloppyDisck
Author-email: guy.garcia@upr.edu
License: MIT
Download-URL: https://github.com/FloppyDisck/e-ink-lib/archive/0.1.1.tar.gz
Keywords: waveshare,eink,e-ink,w-eink
Platform: UNKNOWN
Classifier: Development Status :: 5 - Production/Stable
Classifier: Intended Audience :: Developers
Classifier: Topic :: Software Development :: Build Tools
Classifier: License :: OSI Approved :: MIT License
Classifier: Programming Language :: Python :: 3
Classifier: Programming Language :: Python :: 3.4
Classifier: Programming Language :: Python :: 3.5
Classifier: Programming Language :: Python :: 3.6
